odoo/addons/bi_sql_editor_server_actions/README.rst
odoo/addons/bi_sql_editor_server_actions/__init__.py
odoo/addons/bi_sql_editor_server_actions/__manifest__.py
odoo/addons/bi_sql_editor_server_actions/i18n/bi_sql_editor_server_actions.pot
odoo/addons/bi_sql_editor_server_actions/models/__init__.py
odoo/addons/bi_sql_editor_server_actions/models/bi_sql_view.py
odoo/addons/bi_sql_editor_server_actions/models/ir_actions_server.py
odoo/addons/bi_sql_editor_server_actions/readme/CONTRIBUTORS.rst
odoo/addons/bi_sql_editor_server_actions/readme/DESCRIPTION.rst
odoo/addons/bi_sql_editor_server_actions/static/description/icon.png
odoo/addons/bi_sql_editor_server_actions/static/description/index.html
odoo/addons/bi_sql_editor_server_actions/tests/__init__.py
odoo/addons/bi_sql_editor_server_actions/tests/test_bi_sql_view_server_action.py
odoo/addons/bi_sql_editor_server_actions/views/ir_actions_server_view.xml
odoo/addons/bi_sql_editor_server_actions/views/view_bi_sql_view.xml
odoo13_addon_bi_sql_editor_server_actions-13.0.1.0.2.dev5.dist-info/METADATA
odoo13_addon_bi_sql_editor_server_actions-13.0.1.0.2.dev5.dist-info/WHEEL
odoo13_addon_bi_sql_editor_server_actions-13.0.1.0.2.dev5.dist-info/top_level.txt
odoo13_addon_bi_sql_editor_server_actions-13.0.1.0.2.dev5.dist-info/RECORD
