Metadata-Version: 2.1
Name: odoo13-addon-bi-sql-editor-server-actions
Version: 13.0.1.0.2.dev5
Summary: Add server actions on BI Views builder module
Home-page: https://github.com/OCA/reporting-engine
Author: GRAP,Odoo Community Association (OCA)
Author-email: support@odoo-community.org
License: AGPL-3
Platform: UNKNOWN
Classifier: Programming Language :: Python
Classifier: Framework :: Odoo
Classifier: Framework :: Odoo :: 13.0
Classifier: License :: OSI Approved :: GNU Affero General Public License v3
Requires-Python: >=3.5
Requires-Dist: odoo13-addon-bi-sql-editor
Requires-Dist: odoo <13.1dev,>=13.0a
